gunicorn/__init__.py
gunicorn/__main__.py
gunicorn/arbiter.py
gunicorn/config.py
gunicorn/debug.py
gunicorn/errors.py
gunicorn/glogging.py
gunicorn/pidfile.py
gunicorn/reloader.py
gunicorn/sock.py
gunicorn/systemd.py
gunicorn/util.py
gunicorn/app/__init__.py
gunicorn/app/base.py
gunicorn/app/pasterapp.py
gunicorn/app/wsgiapp.py
gunicorn/http/__init__.py
gunicorn/http/body.py
gunicorn/http/errors.py
gunicorn/http/message.py
gunicorn/http/parser.py
gunicorn/http/unreader.py
gunicorn/http/wsgi.py
gunicorn/instrument/__init__.py
gunicorn/instrument/statsd.py
gunicorn/workers/__init__.py
gunicorn/workers/base.py
gunicorn/workers/base_async.py
gunicorn/workers/geventlet.py
gunicorn/workers/ggevent.py
gunicorn/workers/gthread.py
gunicorn/workers/gtornado.py
gunicorn/workers/sync.py
gunicorn/workers/workertmp.py
gunicorn-22.0.0.dist-info/LICENSE
gunicorn-22.0.0.dist-info/METADATA
gunicorn-22.0.0.dist-info/WHEEL
gunicorn-22.0.0.dist-info/entry_points.txt
gunicorn-22.0.0.dist-info/top_level.txt
gunicorn-22.0.0.dist-info/RECORD
