Metadata-Version: 2.1
Name: gunicorn
Version: 22.0.0
Summary: WSGI HTTP Server for UNIX
Author-email: Benoit Chesneau <benoitc@gunicorn.org>
License: MIT
Project-URL: Homepage, https://gunicorn.org
Project-URL: Documentation, https://docs.gunicorn.org
Project-URL: Issue tracker, https://github.com/benoitc/gunicorn/issues
Project-URL: Source code, https://github.com/benoitc/gunicorn
Project-URL: Changelog, https://docs.gunicorn.org/en/stable/news.html
Classifier: Development Status :: 5 - Production/Stable
Classifier: Environment :: Other Environment
Classifier: Intended Audience :: Developers
Classifier: License :: OSI Approved :: MIT License
Classifier: Operating System :: MacOS :: MacOS X
Classifier: Operating System :: POSIX
Classifier: Programming Language :: Python
Classifier: Programming Language :: Python :: 3
Classifier: Programming Language :: Python :: 3.7
Classifier: Programming Language :: Python :: 3.8
Classifier: Programming Language :: Python :: 3.9
Classifier: Programming Language :: Python :: 3.10
Classifier: Programming Language :: Python :: 3.11
Classifier: Programming Language :: Python :: 3.12
Classifier: Programming Language :: Python :: 3 :: Only
Classifier: Programming Language :: Python :: Implementation :: CPython
Classifier: Programming Language :: Python :: Implementation :: PyPy
Classifier: Topic :: Internet
Classifier: Topic :: Utilities
Classifier: Topic :: Software Development :: Libraries :: Python Modules
Classifier: Topic :: Internet :: WWW/HTTP
Classifier: Topic :: Internet :: WWW/HTTP :: WSGI
Classifier: Topic :: Internet :: WWW/HTTP :: WSGI :: Server
Classifier: Topic :: Internet :: WWW/HTTP :: Dynamic Content
Requires-Python: >=3.7
License-File: LICENSE
Requires-Dist: importlib_metadata; python_version < "3.8"
Requires-Dist: packaging
Provides-Extra: gevent
Requires-Dist: gevent>=1.4.0; extra == "gevent"
Provides-Extra: eventlet
Requires-Dist: eventlet!=0.36.0,>=0.24.1; extra == "eventlet"
Provides-Extra: tornado
Requires-Dist: tornado>=0.2; extra == "tornado"
Provides-Extra: gthread
Provides-Extra: setproctitle
Requires-Dist: setproctitle; extra == "setproctitle"
Provides-Extra: testing
Requires-Dist: gevent; extra == "testing"
Requires-Dist: eventlet; extra == "testing"
Requires-Dist: coverage; extra == "testing"
Requires-Dist: pytest; extra == "testing"
Requires-Dist: pytest-cov; extra == "testing"
